icepay/__init__.py
icepay/client.py
icepay/test.py
icepay_python-0.4.0.dist-info/DESCRIPTION.rst
icepay_python-0.4.0.dist-info/METADATA
icepay_python-0.4.0.dist-info/RECORD
icepay_python-0.4.0.dist-info/WHEEL
icepay_python-0.4.0.dist-info/metadata.json
icepay_python-0.4.0.dist-info/top_level.txt
