Metadata-Version: 2.0
Name: icepay-python
Version: 0.4.0
Summary: A client for Icepay Rest API
Home-page: https://github.com/Producters/icepay-python
Author: Domas Lapinskas
Author-email: domasx2@gmail.com
License: MIT
Keywords: icepay
Platform: UNKNOWN
Classifier: Development Status :: 3 - Alpha
Classifier: Intended Audience :: Developers
Classifier: Topic :: Office/Business :: Financial :: Point-Of-Sale
Classifier: License :: OSI Approved :: MIT License
Classifier: Programming Language :: Python :: 3
Classifier: Programming Language :: Python :: 3.3
Classifier: Programming Language :: Python :: 3.4
Classifier: Programming Language :: Python :: 3.5
Requires-Dist: requests (>=2.11.1)
